{
  "currentVersion": "v_5.0.3",
  "versionIndex": {
    "v_0.0.0": "0",
    "v_5.0.0": "1",
    "v_5.0.1": "2",
    "v_5.0.2": "3",
    "v_5.0.3": "4"
  },
  "versionDetailList": [
    {
      "version": "v_0.0.0",
      "title": "UI细节调整，优化依赖和资源链接",
      "log": "● UI细节调整\n● 优化了maven依赖\n● 调整了资源链接\n"
    },
    {
      "version": "v_5.0.0",
      "title": "5.0全新改版升级",
      "log": "● 新增任务机制\n● 多账号模式\n● 简化交互流程\n● UI调整，沉浸式窗口，优化macOS下体验\n● 更多细节等你发现\n● 该版本重构改动较大，未经充分测试，有问题可退回使用4.x版本，之前的数据还在\n"
    },
    {
      "version": "v_5.0.1",
      "title": "针对5.0新版多处修复和优化",
      "log": "● 任务：修复任务执行状态更新不及时的问题\n● 窗口：优化esc键最小化后窗口再次恢复的表现\n● 修复excel导入提示缺少依赖的问题\n● 任务：修复任务详情成功失败文件路径不实时显示的问题\n● 增加执行前重新导入目标用户功能\n● 任务详情增加模式和线程数等更多细节展示\n"
    },
    {
      "version": "v_5.0.2",
      "title": "增加支持腾讯云短信3.0",
      "log": "● 增加支持腾讯云短信3.0，由于没有条件，无法充分验证\n● 企业微信消息：支持私有化部署时BaseApiUrl配置\n● 全局：优化窗口关闭时的行为，避免再次点击任务栏图标无法唤出窗口\n"
    },
    {
      "version": "v_5.0.3",
      "title": "使用Java21虚拟线程",
      "log": "● 全局：升级Java版本至Java21\n● 推送：固定线程模式下使用虚拟线程，线程数可以放心随意增大\n● 推送：支持设置推送间隔，避免超过频率限制\n● 消息：邮件，修复消息编辑tab邮件正文回显不正确的问题\n● 消息：企业微信，修复消息编辑tab内容回显不正确的问题\n● 消息：企业微信，修复初始打开时 “图文消息编辑框不一致” 问题\n● 任务：去掉保存成功时的弹框提示\n● 账号：企业微信，修复初始打开时 “私有BaseApiUrl” 可见性问题\n"
    }
  ]
}